cache_llm/__init__.py
cache_llm/cache_manager.py
cache_llm/chat_model.py
cache_llm/client_manager.py
cache_llm/embedding_model.py
cache_llm/rag_model.py
cache_llm/rate_limiter.py
cache_llm/rerank_model.py
cache_llm/types.py
cache_llm/config/__init__.py
cache_llm/config/app_config.py
cache_llm/config/rag_config.py
cache_llm/config/rag_config_template.py
cache_llm/config/update_limiter.py
cache_llm-0.1.1.1.dist-info/METADATA
cache_llm-0.1.1.1.dist-info/WHEEL
cache_llm-0.1.1.1.dist-info/top_level.txt
cache_llm-0.1.1.1.dist-info/RECORD
