Metadata-Version: 2.1
Name: cache-llm
Version: 0.1.1.1
Summary: A simple cache for LLM
Home-page: https://github.com/li-xiu-qi/cache-llm
Author: li-xiu-qi
Author-email: lixiuqixiaoke@qq.com
Classifier: Programming Language :: Python :: 3
Classifier: License :: OSI Approved :: MIT License
Classifier: Operating System :: OS Independent
Requires-Python: >=3.6
Requires-Dist: aiohttp==3.10.10
Requires-Dist: diskcache==5.6.3
Requires-Dist: openai==1.52.0
Requires-Dist: pydantic==2.9.2
Requires-Dist: setuptools==75.1.0
